tttest/__init__.py
tttest/main.py
tttest/run.py
tttest/version.py
tttest/cli/__init__.py
tttest/cli/cli_run.py
tttest/config/__init__.py
tttest/config/cfg.py
tttest/core/__init__.py
tttest/core/core.py
tttest/core/wrapper/__init__.py
tttest/core/wrapper/singleton.py
tttest/serve/__init__.py
tttest/serve/api_serve.py
tttest/serve/mock_serve.py
tttest/serve/routes/__init__.py
tttest/utils/__init__.py
tttest/utils/common.py
tttest/utils/utils.py
tttest_cli-1.0.8.dist-info/LICENSE
tttest_cli-1.0.8.dist-info/METADATA
tttest_cli-1.0.8.dist-info/WHEEL
tttest_cli-1.0.8.dist-info/entry_points.txt
tttest_cli-1.0.8.dist-info/top_level.txt
tttest_cli-1.0.8.dist-info/RECORD
